edx_games-1.0.8.dist-info/licenses/LICENSE
games/__init__.py
games/constants.py
games/games.py
games/toggles.py
games/utils.py
games/handlers/__init__.py
games/handlers/common.py
games/handlers/flashcards.py
games/handlers/matching.py
games/locale/README.md
games/locale/config.yaml
games/locale/en/LC_MESSAGES/django.mo
games/locale/en/LC_MESSAGES/django.po
games/locale/es_419/LC_MESSAGES/django.mo
games/locale/es_419/LC_MESSAGES/django.po
games/static/README.txt
games/static/css/confetti.css
games/static/css/flashcards.css
games/static/css/matching.css
games/static/html/flashcards.html
games/static/html/matching.html
games/static/js/src/confetti.js
games/static/js/src/flashcards.js
games/static/js/src/matching.js
edx_games-1.0.8.dist-info/METADATA
edx_games-1.0.8.dist-info/WHEEL
edx_games-1.0.8.dist-info/entry_points.txt
edx_games-1.0.8.dist-info/top_level.txt
edx_games-1.0.8.dist-info/RECORD
