Metadata-Version: 2.4
Name: edx-games
Version: 1.0.8
Summary: Interactive games XBlock for Open edX - Create flashcards and matching games with image support
Home-page: https://github.com/edx/gamesxblock
Author: edX
Author-email: edx@edx.org
License: AGPL v3
License-File: LICENSE
Requires-Dist: XBlock>=1.2.0
Requires-Dist: web-fragments>=0.3.0
Requires-Dist: Django>=2.2
Requires-Dist: django-waffle==5.0.0
Requires-Dist: edx-toggles==5.4.1
Requires-Dist: cryptography>=3.4.8
Dynamic: author
Dynamic: author-email
Dynamic: home-page
Dynamic: license
Dynamic: license-file
Dynamic: requires-dist
Dynamic: summary
